askpy/__init__.py
askpy/compat.py
askpy/exceptions.py
askpy/prompt.py
askpy/question.py
askpy/validation.py
askpy-0.0.4.dist-info/DESCRIPTION.rst
askpy-0.0.4.dist-info/METADATA
askpy-0.0.4.dist-info/RECORD
askpy-0.0.4.dist-info/WHEEL
askpy-0.0.4.dist-info/metadata.json
askpy-0.0.4.dist-info/top_level.txt
